habu_api/__init__.py
habu_api/cleanRoom.py
habu_python_api-2.0.3.dist-info/METADATA
habu_python_api-2.0.3.dist-info/WHEEL
habu_python_api-2.0.3.dist-info/top_level.txt
habu_python_api-2.0.3.dist-info/RECORD
